{
"meta":{"test_sets":[],"test_metrics":[],"learn_metrics":[{"best_value":"Min","name":"Logloss"}],"launch_mode":"Train","parameters":"","iteration_count":30,"learn_sets":["learn"],"name":"experiment"},
"iterations":[
{"learn":[0.6930106882],"iteration":0,"passed_time":0.03929361843,"remaining_time":1.139514934},
{"learn":[0.6928732512],"iteration":1,"passed_time":0.0682423642,"remaining_time":0.9553930988},
{"learn":[0.6927376393],"iteration":2,"passed_time":0.1253539765,"remaining_time":1.128185789},
{"learn":[0.6925972726],"iteration":3,"passed_time":0.2355169692,"remaining_time":1.530860299},
{"learn":[0.6924538992],"iteration":4,"passed_time":0.2557950506,"remaining_time":1.278975253},
{"learn":[0.6922838779],"iteration":5,"passed_time":0.2772558302,"remaining_time":1.109023321},
{"learn":[0.6921494985],"iteration":6,"passed_time":0.3003719773,"remaining_time":0.9869364967},
{"learn":[0.6920186817],"iteration":7,"passed_time":0.3190487171,"remaining_time":0.8773839721},
{"learn":[0.6918786143],"iteration":8,"passed_time":0.3375382367,"remaining_time":0.7875892189},
{"learn":[0.6917578957],"iteration":9,"passed_time":0.3559142615,"remaining_time":0.711828523},
{"learn":[0.6916047077],"iteration":10,"passed_time":0.3736957644,"remaining_time":0.6454745022},
{"learn":[0.6914632717],"iteration":11,"passed_time":0.3946634628,"remaining_time":0.5919951942},
{"learn":[0.6913328659],"iteration":12,"passed_time":0.4150956414,"remaining_time":0.5428173772},
{"learn":[0.6912152867],"iteration":13,"passed_time":0.4529780596,"remaining_time":0.517689211},
{"learn":[0.691064068],"iteration":14,"passed_time":0.4913352303,"remaining_time":0.4913352303},
{"learn":[0.6909164252],"iteration":15,"passed_time":0.5326874292,"remaining_time":0.4661015005},
{"learn":[0.6907823565],"iteration":16,"passed_time":0.5726936429,"remaining_time":0.4379421975},
{"learn":[0.6906054479],"iteration":17,"passed_time":0.6081949065,"remaining_time":0.405463271},
{"learn":[0.6904529952],"iteration":18,"passed_time":0.6573424963,"remaining_time":0.3805667084},
{"learn":[0.6903015405],"iteration":19,"passed_time":0.6941180152,"remaining_time":0.3470590076},
{"learn":[0.6901698102],"iteration":20,"passed_time":0.7321567617,"remaining_time":0.3137814693},
{"learn":[0.6900012579],"iteration":21,"passed_time":0.7510226902,"remaining_time":0.2730991601},
{"learn":[0.6898674358],"iteration":22,"passed_time":0.7695443025,"remaining_time":0.2342091355},
{"learn":[0.6897290547],"iteration":23,"passed_time":0.7876587635,"remaining_time":0.1969146909},
{"learn":[0.6896095005],"iteration":24,"passed_time":0.8119756043,"remaining_time":0.1623951209},
{"learn":[0.6894499605],"iteration":25,"passed_time":0.8481961837,"remaining_time":0.1304917206},
{"learn":[0.6893272917],"iteration":26,"passed_time":0.8743130571,"remaining_time":0.09714589523},
{"learn":[0.6891762759],"iteration":27,"passed_time":0.9006418902,"remaining_time":0.06433156359},
{"learn":[0.689043459],"iteration":28,"passed_time":0.9341298881,"remaining_time":0.03221137545},
{"learn":[0.688905045],"iteration":29,"passed_time":0.9700011081,"remaining_time":0}
]}